cmem_plugin_kafka/__init__.py
cmem_plugin_kafka/constants.py
cmem_plugin_kafka/kafka_handlers.py
cmem_plugin_kafka/utils.py
cmem_plugin_kafka/workflow/__init__.py
cmem_plugin_kafka/workflow/consumer.py
cmem_plugin_kafka/workflow/producer.py
cmem_plugin_kafka-3.4.0.dist-info/METADATA
cmem_plugin_kafka-3.4.0.dist-info/WHEEL
cmem_plugin_kafka-3.4.0.dist-info/licenses/LICENSE
cmem_plugin_kafka-3.4.0.dist-info/RECORD
