Metadata-Version: 2.4
Name: cmem-plugin-kafka
Version: 3.4.0
Summary: Send and receive messages from Apache Kafka.
License: Apache-2.0
License-File: LICENSE
Keywords: eccenca Corporate Memory,plugin,kafka,kafka-producer,kafka-consumer
Author: eccenca GmbH
Author-email: cmempy-developer@eccenca.com
Requires-Python: >=3.13,<4.0
Classifier: Development Status :: 5 - Production/Stable
Classifier: Environment :: Plugins
Classifier: Intended Audience :: Information Technology
Classifier: License :: OSI Approved :: Apache Software License
Classifier: Programming Language :: Python :: 3
Classifier: Programming Language :: Python :: 3.13
Classifier: Programming Language :: Python :: 3.14
Classifier: Topic :: Software Development :: Libraries :: Python Modules
Requires-Dist: cmem-cmempy (>=25.3.0,<26.0.0)
Requires-Dist: cmem-plugin-base (>=4.12.1,<5.0.0)
Requires-Dist: confluent-kafka (>=2.6.0,<3.0.0)
Requires-Dist: defusedxml (>=0.7.1,<0.8.0)
Requires-Dist: json-stream (==2.3.0)
Requires-Dist: requests (>=2.32.5,<3.0.0)
Project-URL: Homepage, https://github.com/eccenca/cmem-plugin-kafka
